multiline/__init__.py
multiline/multiline_json_parser.py
multiline-1.0.1.dist-info/METADATA
multiline-1.0.1.dist-info/WHEEL
multiline-1.0.1.dist-info/top_level.txt
multiline-1.0.1.dist-info/RECORD
