Metadata-Version: 2.1
Name: multiline
Version: 1.0.1
Summary: A package to read multline json values
Home-page: https://github.com/open-source-python/multiline.git
Author: Sanket Tantia
Author-email: tantiasanket@gmail.com
License: UNKNOWN
Platform: UNKNOWN
Classifier: Programming Language :: Python :: 3
Classifier: License :: OSI Approved :: MIT License
Classifier: Operating System :: OS Independent
